{
  "resourceType": "ValueSet",
  "status": "active",
  "name": "RadiologyLaterality",
  "id": "radiology-laterality-1.0.0",
  "title": "Radiology Laterality",
  "description": "The Radiology Body Structure Laterality value set includes SNOMED CT that can be used for body structure laterailty in a ServiceRequest.",
  "url": "http://csiro.au/fhir/ValueSet/radiology-laterality",
  "version": "1.0.0",  
  "experimental": false,
  "date": "2024-03-31",
  "publisher": "Sparked FHIR Accelerator",
  "contact": [
    {
      "telecom": [
        {
          "system": "email",
          "value": "fhir@csiro.au"
        }
      ]
    }
  ],
  "compose": {    
      "include": [
        {
          "system": "http://snomed.info/sct",
          "concept": [
          ]  
        }
      ]
  }
}
